README.rst
setup.py
wishbone_output_tcp/__init__.py
wishbone_output_tcp/tcpout.py
wishbone_output_tcp.egg-info/PKG-INFO
wishbone_output_tcp.egg-info/SOURCES.txt
wishbone_output_tcp.egg-info/dependency_links.txt
wishbone_output_tcp.egg-info/entry_points.txt
wishbone_output_tcp.egg-info/namespace_packages.txt
wishbone_output_tcp.egg-info/not-zip-safe
wishbone_output_tcp.egg-info/requires.txt
wishbone_output_tcp.egg-info/top_level.txt